{"answers":[{"answerContent":{"boundingBox":{"boundingBoxes":[{"height":689,"label":"lock","left":2011,"top":1239,"width":835},{"height":2592,"label":"handle","left":1594,"top":348,"width":875},{"height":604,"label":"lock","left":2496,"top":0,"width":714},{"height":280,"label":"lock","left":1270,"top":0,"width":795},{"height":378,"label":"lock","left":651,"top":10,"width":390}],"inputImageProperties":{"height":3024,"width":4032}}},"submissionTime":"2020-05-09T08:15:48Z","workerId":"public.us-east-1.A16GH5GPKBX5GA"},{"answerContent":{"boundingBox":{"boundingBoxes":[{"height":448,"label":"lock","left":1958,"top":2576,"width":1231},{"height":562,"label":"lock","left":2050,"top":1322,"width":693},{"height":2485,"label":"handle","left":1735,"top":375,"width":701},{"height":644,"label":"lock","left":2512,"top":0,"width":623},{"height":498,"label":"lock","left":704,"top":0,"width":1246}],"inputImageProperties":{"height":3024,"width":4032}}},"submissionTime":"2020-05-09T08:22:00Z","workerId":"public.us-east-1.A2Z5MTI93FAICS"},{"answerContent":{"boundingBox":{"boundingBoxes":[{"height":527,"label":"lock","left":2504,"top":21,"width":597},{"height":474,"label":"lock","left":2065,"top":1357,"width":650},{"height":454,"label":"lock","left":2153,"top":2570,"width":1018},{"height":2356,"label":"handle","left":1819,"top":460,"width":597}],"inputImageProperties":{"height":3024,"width":4032}}},"submissionTime":"2020-05-09T08:26:25Z","workerId":"public.us-east-1.A2L9QL5S7KUL6V"}]}