{"answers":[{"answerContent":{"boundingBox":{"boundingBoxes":[{"height":486,"label":"lock","left":1703,"top":848,"width":538},{"height":1248,"label":"lock","left":747,"top":0,"width":1286},{"height":487,"label":"lock","left":591,"top":813,"width":330},{"height":417,"label":"lock","left":1321,"top":1873,"width":451},{"height":1616,"label":"handle","left":1025,"top":1317,"width":452}],"inputImageProperties":{"height":3024,"width":4032}}},"submissionTime":"2020-05-09T08:30:39Z","workerId":"public.us-east-1.A16GH5GPKBX5GA"},{"answerContent":{"boundingBox":{"boundingBoxes":[{"height":1207,"label":"lock","left":858,"top":5,"width":1145},{"height":468,"label":"lock","left":1725,"top":815,"width":427},{"height":1583,"label":"handle","left":1072,"top":1339,"width":361},{"height":340,"label":"lock","left":1384,"top":1908,"width":356},{"height":80,"label":"lock","left":1299,"top":2944,"width":426},{"height":547,"label":"lock","left":631,"top":701,"width":192}],"inputImageProperties":{"height":3024,"width":4032}}},"submissionTime":"2020-05-09T08:40:45Z","workerId":"public.us-east-1.A29JU2TL3NJ796"},{"answerContent":{"boundingBox":{"boundingBoxes":[{"height":1120,"label":"lock","left":766,"top":165,"width":1398},{"height":1567,"label":"handle","left":1081,"top":1356,"width":329},{"height":313,"label":"lock","left":1387,"top":1912,"width":361}],"inputImageProperties":{"height":3024,"width":4032}}},"submissionTime":"2020-05-09T08:41:07Z","workerId":"public.us-east-1.AGO9QN7UEDUYL"}]}