[{"datasetObjectId":"901","consolidatedAnnotation":{"content":{"lock-handle-metadata":{"job-name":"labeling-job/label-locks-and-handles-on-boxes","class-map":{"1":"handle","0":"lock"},"human-annotated":"yes","objects":[{"confidence":0.46},{"confidence":0.38},{"confidence":0.41},{"confidence":0.09},{"confidence":0.27},{"confidence":0.09},{"confidence":0.18},{"confidence":0.36}],"creation-date":"2020-05-09T12:32:51.594986","type":"groundtruth/object-detection"},"lock-handle":{"annotations":[{"class_id":0,"width":1820.0,"top":973.0,"height":1283.0,"left":543.6666666666666},{"class_id":0,"width":976.3333333333334,"top":559.6666666666665,"height":410.0,"left":900.6666666666666},{"class_id":0,"width":762.3333333333333,"top":538.0,"height":634.3333333333333,"left":195.33333333333334},{"class_id":0,"width":328,"top":688,"height":197,"left":852},{"class_id":0,"width":322.5,"top":2308.5,"height":359.5,"left":1124.0},{"class_id":0,"width":392,"top":2798,"height":226,"left":1544},{"class_id":0,"width":185.0,"top":533.0,"height":170.0,"left":137.0},{"class_id":1,"width":449.33333333333337,"top":1834.3333333333333,"height":1177.6666666666667,"left":804.3333333333334}],"image_size":[{"width":4032,"depth":3,"height":3024}]}}}}]