{"answers":[{"answerContent":{"boundingBox":{"boundingBoxes":[{"height":908,"label":"handle","left":968,"top":2373,"width":233},{"height":3353,"label":"lock","left":878,"top":121,"width":1782}],"inputImageProperties":{"height":4032,"width":3024}}},"submissionTime":"2020-05-09T08:17:45Z","workerId":"public.us-east-1.A2L9QL5S7KUL6V"},{"answerContent":{"boundingBox":{"boundingBoxes":[{"height":880,"label":"handle","left":955,"top":2378,"width":333},{"height":932,"label":"lock","left":808,"top":1718,"width":940},{"height":1466,"label":"lock","left":1278,"top":137,"width":334},{"height":796,"label":"lock","left":881,"top":797,"width":303}],"inputImageProperties":{"height":4032,"width":3024}}},"submissionTime":"2020-05-09T08:41:50Z","workerId":"public.us-east-1.AGO9QN7UEDUYL"},{"answerContent":{"boundingBox":{"boundingBoxes":[{"height":1496,"label":"lock","left":1260,"top":113,"width":420},{"height":830,"label":"lock","left":841,"top":756,"width":349},{"height":946,"label":"lock","left":865,"top":1715,"width":885},{"height":970,"label":"handle","left":946,"top":2311,"width":350}],"inputImageProperties":{"height":4032,"width":3024}}},"submissionTime":"2020-05-09T09:03:42Z","workerId":"public.us-east-1.A30NZAZ04OUGQD"}]}