{"answers":[{"answerContent":{"boundingBox":{"boundingBoxes":[{"height":713,"label":"lock","left":995,"top":120,"width":1398},{"height":1471,"label":"handle","left":1155,"top":833,"width":702},{"height":525,"label":"lock","left":1327,"top":2260,"width":735},{"height":559,"label":"lock","left":636,"top":164,"width":326}],"inputImageProperties":{"height":3024,"width":4032}}},"submissionTime":"2020-05-09T08:16:37Z","workerId":"public.us-east-1.A1T1FK3P2N408U"},{"answerContent":{"boundingBox":{"boundingBoxes":[{"height":566,"label":"lock","left":656,"top":143,"width":265},{"height":689,"label":"lock","left":921,"top":126,"width":1521},{"height":548,"label":"lock","left":1381,"top":2213,"width":690},{"height":336,"label":"lock","left":1470,"top":1346,"width":424},{"height":1521,"label":"handle","left":1240,"top":815,"width":353}],"inputImageProperties":{"height":3024,"width":4032}}},"submissionTime":"2020-05-09T08:17:11Z","workerId":"public.us-east-1.AATL9DKBHXYW9"},{"answerContent":{"boundingBox":{"boundingBoxes":[{"height":640,"label":"handle","left":1094,"top":121,"width":1599},{"height":1460,"label":"handle","left":1216,"top":796,"width":730},{"height":383,"label":"lock","left":1373,"top":2377,"width":591}],"inputImageProperties":{"height":3024,"width":4032}}},"submissionTime":"2020-05-09T08:27:33Z","workerId":"public.us-east-1.AME98XVLFFLCH"}]}