{"answers":[{"answerContent":{"boundingBox":{"boundingBoxes":[{"height":588,"label":"handle","left":979,"top":2103,"width":992},{"height":734,"label":"handle","left":1108,"top":2611,"width":267},{"height":741,"label":"lock","left":899,"top":1204,"width":1105}],"inputImageProperties":{"height":4032,"width":3024}}},"submissionTime":"2020-05-09T08:27:55Z","workerId":"public.us-east-1.A3LG5VYLSXRDZ7"},{"answerContent":{"boundingBox":{"boundingBoxes":[{"height":718,"label":"handle","left":1114,"top":2593,"width":236},{"height":565,"label":"lock","left":981,"top":2121,"width":911},{"height":751,"label":"lock","left":889,"top":1207,"width":1104}],"inputImageProperties":{"height":4032,"width":3024}}},"submissionTime":"2020-05-09T08:58:21Z","workerId":"public.us-east-1.A3KKENI2RQO12O"},{"answerContent":{"boundingBox":{"boundingBoxes":[{"height":767,"label":"lock","left":910,"top":1214,"width":1076},{"height":656,"label":"lock","left":969,"top":2062,"width":980},{"height":767,"label":"handle","left":1139,"top":2578,"width":213}],"inputImageProperties":{"height":4032,"width":3024}}},"submissionTime":"2020-05-09T09:07:05Z","workerId":"public.us-east-1.A1T1FK3P2N408U"}]}