{"answers":[{"answerContent":{"boundingBox":{"boundingBoxes":[{"height":1026,"label":"lock","left":680,"top":1734,"width":2153},{"height":746,"label":"lock","left":133,"top":1283,"width":451},{"height":189,"label":"lock","left":584,"top":1239,"width":467},{"height":401,"label":"lock","left":923,"top":1107,"width":1267},{"height":110,"label":"handle","left":1194,"top":2911,"width":282}],"inputImageProperties":{"height":3024,"width":4032}}},"submissionTime":"2020-05-09T16:50:03Z","workerId":"public.us-east-1.AMMQXXASJ9Q2W"},{"answerContent":{"boundingBox":{"boundingBoxes":[{"height":1044,"label":"lock","left":631,"top":1723,"width":2224},{"height":411,"label":"lock","left":887,"top":1106,"width":1322},{"height":803,"label":"lock","left":13,"top":1240,"width":597},{"height":212,"label":"lock","left":602,"top":1220,"width":427},{"height":115,"label":"handle","left":1093,"top":2909,"width":426}],"inputImageProperties":{"height":3024,"width":4032}}},"submissionTime":"2020-05-09T17:02:48Z","workerId":"public.us-east-1.A18AFAGSYXS8R7"},{"answerContent":{"boundingBox":{"boundingBoxes":[{"height":774,"label":"lock","left":0,"top":1259,"width":603},{"height":199,"label":"lock","left":567,"top":1228,"width":500},{"height":400,"label":"lock","left":919,"top":1101,"width":1274},{"height":1047,"label":"lock","left":671,"top":1712,"width":2146}],"inputImageProperties":{"height":3023,"width":4032}}},"submissionTime":"2020-05-09T17:45:22Z","workerId":"public.us-east-1.A2NEEM4JRMR4BB"}]}