{"answers":[{"answerContent":{"boundingBox":{"boundingBoxes":[{"height":1264,"label":"handle","left":69,"top":0,"width":754},{"height":242,"label":"lock","left":787,"top":0,"width":754},{"height":944,"label":"lock","left":47,"top":1326,"width":2573}],"inputImageProperties":{"height":3024,"width":4032}}},"submissionTime":"2020-05-09T08:58:30Z","workerId":"public.us-east-1.A29JU2TL3NJ796"},{"answerContent":{"boundingBox":{"boundingBoxes":[{"height":949,"label":"lock","left":55,"top":1313,"width":2573},{"height":1248,"label":"handle","left":94,"top":16,"width":681},{"height":260,"label":"lock","left":785,"top":6,"width":691}],"inputImageProperties":{"height":3024,"width":4032}}},"submissionTime":"2020-05-09T09:27:29Z","workerId":"public.us-east-1.A29OJFPXJP5ODV"},{"answerContent":{"boundingBox":{"boundingBoxes":[{"height":939,"label":"lock","left":100,"top":1337,"width":2526},{"height":1276,"label":"handle","left":100,"top":0,"width":1410}],"inputImageProperties":{"height":3024,"width":4032}}},"submissionTime":"2020-05-09T09:35:10Z","workerId":"public.us-east-1.ASM06EV1KY10G"}]}