[{"datasetObjectId":"770","dataObject":{"s3Uri":"s3://boxlocks/box_images/IMG_6279.JPG"},"annotations":[{"workerId":"public.us-east-1.A16GH5GPKBX5GA","annotationData":{"content":"{\"boundingBox\":{\"boundingBoxes\":[{\"height\":495,\"label\":\"lock\",\"left\":1822,\"top\":16,\"width\":562},{\"height\":1379,\"label\":\"handle\",\"left\":1289,\"top\":36,\"width\":628},{\"height\":685,\"label\":\"lock\",\"left\":1431,\"top\":1500,\"width\":1039}],\"inputImageProperties\":{\"height\":3024,\"width\":4032}}}"}},{"workerId":"public.us-east-1.A30NZAZ04OUGQD","annotationData":{"content":"{\"boundingBox\":{\"boundingBoxes\":[{\"height\":552,\"label\":\"lock\",\"left\":1856,\"top\":6,\"width\":491},{\"height\":736,\"label\":\"lock\",\"left\":1444,\"top\":1426,\"width\":1745},{\"height\":1350,\"label\":\"handle\",\"left\":1313,\"top\":23,\"width\":526}],\"inputImageProperties\":{\"height\":3024,\"width\":4032}}}"}},{"workerId":"public.us-east-1.A1T1FK3P2N408U","annotationData":{"content":"{\"boundingBox\":{\"boundingBoxes\":[{\"height\":801,\"label\":\"lock\",\"left\":1487,\"top\":1387,\"width\":1674},{\"height\":514,\"label\":\"lock\",\"left\":1736,\"top\":43,\"width\":624},{\"height\":1354,\"label\":\"handle\",\"left\":1293,\"top\":21,\"width\":547}],\"inputImageProperties\":{\"height\":3024,\"width\":4032}}}"}}]},{"datasetObjectId":"526","dataObject":{"s3Uri":"s3://boxlocks/box_images/IMG_6030.JPG"},"annotations":[{"workerId":"public.us-east-1.AMKGMVI25PC0B","annotationData":{"content":"{\"boundingBox\":{\"boundingBoxes\":[{\"height\":962,\"label\":\"lock\",\"left\":1787,\"top\":550,\"width\":1829},{\"height\":737,\"label\":\"lock\",\"left\":1362,\"top\":44,\"width\":1847},{\"height\":1387,\"label\":\"handle\",\"left\":1687,\"top\":1512,\"width\":701},{\"height\":425,\"label\":\"lock\",\"left\":2019,\"top\":2018,\"width\":488},{\"height\":205,\"label\":\"lock\",\"left\":1769,\"top\":2819,\"width\":726}],\"inputImageProperties\":{\"height\":3024,\"width\":4032}}}"}},{"workerId":"public.us-east-1.ASM06EV1KY10G","annotationData":{"content":"{\"boundingBox\":{\"boundingBoxes\":[{\"height\":907,\"label\":\"lock\",\"left\":1813,\"top\":590,\"width\":1812},{\"height\":425,\"label\":\"lock\",\"left\":2227,\"top\":242,\"width\":990},{\"height\":591,\"label\":\"lock\",\"left\":1492,\"top\":176,\"width\":1167},{\"height\":1327,\"label\":\"handle\",\"left\":1719,\"top\":1563,\"width\":570},{\"height\":217,\"label\":\"lock\",\"left\":1758,\"top\":2807,\"width\":674},{\"height\":199,\"label\":\"lock\",\"left\":1404,\"top\":65,\"width\":227}],\"inputImageProperties\":{\"height\":3024,\"width\":4032}}}"}},{"workerId":"public.us-east-1.A1I0WOGP2D47N","annotationData":{"content":"{\"boundingBox\":{\"boundingBoxes\":[{\"height\":908,\"label\":\"lock\",\"left\":1796,\"top\":616,\"width\":1877},{\"height\":476,\"label\":\"lock\",\"left\":2223,\"top\":154,\"width\":1045},{\"height\":653,\"label\":\"lock\",\"left\":1427,\"top\":140,\"width\":1023},{\"height\":234,\"label\":\"lock\",\"left\":1406,\"top\":55,\"width\":341},{\"height\":348,\"label\":\"lock\",\"left\":2045,\"top\":2078,\"width\":477},{\"height\":172,\"label\":\"lock\",\"left\":1768,\"top\":2845,\"width\":661},{\"height\":1320,\"label\":\"handle\",\"left\":1733,\"top\":1560,\"width\":575}],\"inputImageProperties\":{\"height\":3024,\"width\":4032}}}"}}]},{"datasetObjectId":"861","dataObject":{"s3Uri":"s3://boxlocks/box_images/IMG_6374.JPG"},"annotations":[{"workerId":"public.us-east-1.A3SEI5Z8LVY9J2","annotationData":{"content":"{\"boundingBox\":{\"boundingBoxes\":[{\"height\":1277,\"label\":\"lock\",\"left\":1076,\"top\":113,\"width\":1292},{\"height\":1504,\"label\":\"handle\",\"left\":1198,\"top\":1428,\"width\":345},{\"height\":379,\"label\":\"lock\",\"left\":1465,\"top\":1946,\"width\":446}],\"inputImageProperties\":{\"height\":3024,\"width\":4032}}}"}},{"workerId":"public.us-east-1.A16GH5GPKBX5GA","annotationData":{"content":"{\"boundingBox\":{\"boundingBoxes\":[{\"height\":527,\"label\":\"lock\",\"left\":839,\"top\":793,\"width\":310},{\"height\":1282,\"label\":\"lock\",\"left\":880,\"top\":92,\"width\":1576},{\"height\":432,\"label\":\"lock\",\"left\":1513,\"top\":1900,\"width\":525},{\"height\":1596,\"label\":\"handle\",\"left\":1257,\"top\":1428,\"width\":471}],\"inputImageProperties\":{\"height\":3024,\"width\":4032}}}"}},{"workerId":"public.us-east-1.A30LQHOQAW6PHR","annotationData":{"content":"{\"boundingBox\":{\"boundingBoxes\":[{\"height\":485,\"label\":\"lock\",\"left\":1889,\"top\":898,\"width\":477},{\"height\":538,\"label\":\"lock\",\"left\":843,\"top\":760,\"width\":222},{\"height\":1192,\"label\":\"lock\",\"left\":1035,\"top\":114,\"width\":1123},{\"height\":1524,\"label\":\"handle\",\"left\":1242,\"top\":1414,\"width\":670}],\"inputImageProperties\":{\"height\":3024,\"width\":4032}}}"}}]},{"datasetObjectId":"240","dataObject":{"s3Uri":"s3://boxlocks/box_images/IMG_5647.jpg"},"annotations":[{"workerId":"public.us-east-1.A1PDBRYBFMMFNY","annotationData":{"content":"{\"boundingBox\":{\"boundingBoxes\":[{\"height\":1678,\"label\":\"handle\",\"left\":994,\"top\":1352,\"width\":455}],\"inputImageProperties\":{\"height\":4032,\"width\":3024}}}"}},{"workerId":"public.us-east-1.A16GH5GPKBX5GA","annotationData":{"content":"{\"boundingBox\":{\"boundingBoxes\":[{\"height\":2052,\"label\":\"handle\",\"left\":738,\"top\":1166,\"width\":1026}],\"inputImageProperties\":{\"height\":4032,\"width\":3024}}}"}},{"workerId":"public.us-east-1.A30NZAZ04OUGQD","annotationData":{"content":"{\"boundingBox\":{\"boundingBoxes\":[{\"height\":1706,\"label\":\"handle\",\"left\":992,\"top\":1329,\"width\":490}],\"inputImageProperties\":{\"height\":4032,\"width\":3024}}}"}}]}]