{"answers":[{"answerContent":{"boundingBox":{"boundingBoxes":[{"height":709,"label":"lock","left":572,"top":565,"width":370},{"height":285,"label":"lock","left":1439,"top":574,"width":1045},{"height":872,"label":"lock","left":1065,"top":959,"width":2024},{"height":976,"label":"handle","left":1471,"top":2048,"width":746}],"inputImageProperties":{"height":3024,"width":4032}}},"submissionTime":"2020-05-09T16:49:33Z","workerId":"public.us-east-1.A12HQ561AI1UVY"},{"answerContent":{"boundingBox":{"boundingBoxes":[{"height":1010,"label":"lock","left":946,"top":893,"width":2217},{"height":875,"label":"lock","left":53,"top":454,"width":1011},{"height":392,"label":"lock","left":1376,"top":481,"width":1165},{"height":986,"label":"handle","left":1408,"top":2038,"width":585},{"height":357,"label":"lock","left":1712,"top":2661,"width":646}],"inputImageProperties":{"height":3024,"width":4032}}},"submissionTime":"2020-05-09T16:55:54Z","workerId":"public.us-east-1.A8K41IYNVA24I"},{"answerContent":{"boundingBox":{"boundingBoxes":[{"height":935,"label":"lock","left":1051,"top":931,"width":2057},{"height":283,"label":"lock","left":1445,"top":575,"width":1096},{"height":725,"label":"lock","left":533,"top":575,"width":382},{"height":322,"label":"lock","left":1654,"top":2702,"width":604},{"height":962,"label":"handle","left":1482,"top":2062,"width":419}],"inputImageProperties":{"height":3024,"width":4032}}},"submissionTime":"2020-05-09T16:59:05Z","workerId":"public.us-east-1.AME98XVLFFLCH"}]}