{"answers":[{"answerContent":{"boundingBox":{"boundingBoxes":[{"height":692,"label":"lock","left":1031,"top":1918,"width":638},{"height":613,"label":"lock","left":350,"top":1930,"width":687},{"height":328,"label":"lock","left":16,"top":2270,"width":589},{"height":613,"label":"lock","left":0,"top":2398,"width":520},{"height":765,"label":"lock","left":891,"top":2161,"width":1538},{"height":347,"label":"lock","left":2009,"top":2677,"width":918}],"inputImageProperties":{"height":3024,"width":4032}}},"submissionTime":"2020-05-09T16:58:33Z","workerId":"public.us-east-1.A19VF0AVOVX8K3"},{"answerContent":{"boundingBox":{"boundingBoxes":[{"height":361,"label":"lock","left":326,"top":1991,"width":769},{"height":423,"label":"lock","left":1112,"top":1960,"width":577},{"height":539,"label":"lock","left":842,"top":2276,"width":2124},{"height":577,"label":"lock","left":19,"top":2160,"width":469}],"inputImageProperties":{"height":3024,"width":4032}}},"submissionTime":"2020-05-09T16:58:41Z","workerId":"public.us-east-1.A2S7J8ICEO3GRI"},{"answerContent":{"boundingBox":{"boundingBoxes":[{"height":266,"label":"lock","left":2096,"top":2758,"width":791},{"height":728,"label":"lock","left":0,"top":2284,"width":548},{"height":389,"label":"lock","left":429,"top":1997,"width":723},{"height":395,"label":"lock","left":1124,"top":2008,"width":520},{"height":491,"label":"lock","left":1277,"top":2290,"width":898},{"height":372,"label":"lock","left":898,"top":2516,"width":548}],"inputImageProperties":{"height":3024,"width":4032}}},"submissionTime":"2020-05-09T17:27:18Z","workerId":"public.us-east-1.AHNFZWCD02H6B"}]}