{"answers":[{"answerContent":{"boundingBox":{"boundingBoxes":[{"height":528,"label":"lock","left":503,"top":1093,"width":1088},{"height":317,"label":"lock","left":1503,"top":1040,"width":246},{"height":598,"label":"lock","left":1767,"top":847,"width":351},{"height":263,"label":"lock","left":2135,"top":1410,"width":299},{"height":317,"label":"lock","left":2346,"top":1831,"width":351},{"height":351,"label":"lock","left":1837,"top":1902,"width":176},{"height":844,"label":"lock","left":1416,"top":2148,"width":456}],"inputImageProperties":{"height":3024,"width":4032}}},"submissionTime":"2020-05-09T16:51:55Z","workerId":"public.us-east-1.A2L9QL5S7KUL6V"},{"answerContent":{"boundingBox":{"boundingBoxes":[{"height":332,"label":"lock","left":2266,"top":1827,"width":472},{"height":252,"label":"lock","left":2136,"top":1404,"width":326},{"height":780,"label":"lock","left":475,"top":1106,"width":1251},{"height":954,"label":"lock","left":1459,"top":2070,"width":465}],"inputImageProperties":{"height":3024,"width":4032}}},"submissionTime":"2020-05-09T17:06:16Z","workerId":"public.us-east-1.A3PB6LQU7BTNB9"},{"answerContent":{"boundingBox":{"boundingBoxes":[{"height":400,"label":"handle","left":1304,"top":2622,"width":254},{"height":785,"label":"lock","left":427,"top":1106,"width":1308},{"height":407,"label":"lock","left":1504,"top":1045,"width":285},{"height":662,"label":"lock","left":1712,"top":783,"width":454},{"height":277,"label":"lock","left":2150,"top":1383,"width":316},{"height":354,"label":"lock","left":2258,"top":1814,"width":508},{"height":308,"label":"lock","left":2427,"top":2160,"width":308},{"height":940,"label":"lock","left":1458,"top":2084,"width":461},{"height":354,"label":"lock","left":1812,"top":1868,"width":223},{"height":185,"label":"lock","left":1912,"top":2645,"width":192}],"inputImageProperties":{"height":3024,"width":4032}}},"submissionTime":"2020-05-09T17:37:10Z","workerId":"public.us-east-1.A3KKENI2RQO12O"}]}