{"answers":[{"answerContent":{"boundingBox":{"boundingBoxes":[{"height":1255,"label":"lock","left":206,"top":553,"width":809}],"inputImageProperties":{"height":4032,"width":3024}}},"submissionTime":"2020-05-09T08:06:44Z","workerId":"public.us-east-1.A3SEI5Z8LVY9J2"},{"answerContent":{"boundingBox":{"boundingBoxes":[{"height":800,"label":"lock","left":273,"top":573,"width":650},{"height":452,"label":"lock","left":483,"top":1332,"width":471}],"inputImageProperties":{"height":4032,"width":3024}}},"submissionTime":"2020-05-09T08:08:46Z","workerId":"public.us-east-1.A1KF93C9NTOP42"},{"answerContent":{"boundingBox":{"boundingBoxes":[{"height":1246,"label":"lock","left":254,"top":545,"width":700}],"inputImageProperties":{"height":4032,"width":3024}}},"submissionTime":"2020-05-09T09:12:16Z","workerId":"public.us-east-1.AGO9QN7UEDUYL"}]}