{"answers":[{"answerContent":{"boundingBox":{"boundingBoxes":[{"height":792,"label":"lock","left":1554,"top":2,"width":1399},{"height":677,"label":"lock","left":441,"top":0,"width":1091},{"height":1359,"label":"handle","left":1626,"top":876,"width":401}],"inputImageProperties":{"height":3024,"width":4032}}},"submissionTime":"2020-05-09T16:50:38Z","workerId":"public.us-east-1.A3SEI5Z8LVY9J2"},{"answerContent":{"boundingBox":{"boundingBoxes":[{"height":346,"label":"lock","left":2597,"top":737,"width":454},{"height":692,"label":"lock","left":1512,"top":0,"width":2023},{"height":654,"label":"lock","left":373,"top":6,"width":1123},{"height":323,"label":"lock","left":2435,"top":1499,"width":254},{"height":438,"label":"lock","left":2327,"top":2176,"width":169},{"height":331,"label":"lock","left":1666,"top":2337,"width":377},{"height":1347,"label":"handle","left":1651,"top":898,"width":453}],"inputImageProperties":{"height":3024,"width":4032}}},"submissionTime":"2020-05-09T16:51:55Z","workerId":"public.us-east-1.A2S7J8ICEO3GRI"},{"answerContent":{"boundingBox":{"boundingBoxes":[{"height":707,"label":"lock","left":1586,"top":18,"width":1341},{"height":653,"label":"lock","left":430,"top":0,"width":1129},{"height":299,"label":"lock","left":1696,"top":2316,"width":343},{"height":367,"label":"lock","left":2636,"top":683,"width":333},{"height":1342,"label":"handle","left":1639,"top":872,"width":385}],"inputImageProperties":{"height":3024,"width":4032}}},"submissionTime":"2020-05-09T16:52:59Z","workerId":"public.us-east-1.A3Q213DS0LZKQO"}]}