[{"datasetObjectId":"396","dataObject":{"s3Uri":"s3://boxlocks/box_images/IMG_5804.JPG"},"annotations":[{"workerId":"public.us-east-1.A1T1FK3P2N408U","annotationData":{"content":"{\"boundingBox\":{\"boundingBoxes\":[{\"height\":597,\"label\":\"lock\",\"left\":1680,\"top\":214,\"width\":1128},{\"height\":160,\"label\":\"lock\",\"left\":2222,\"top\":109,\"width\":83},{\"height\":448,\"label\":\"lock\",\"left\":1343,\"top\":192,\"width\":243},{\"height\":133,\"label\":\"lock\",\"left\":1200,\"top\":330,\"width\":187},{\"height\":276,\"label\":\"lock\",\"left\":1951,\"top\":1182,\"width\":354},{\"height\":420,\"label\":\"lock\",\"left\":1868,\"top\":1889,\"width\":475},{\"height\":1143,\"label\":\"handle\",\"left\":1829,\"top\":740,\"width\":270}],\"inputImageProperties\":{\"height\":3024,\"width\":4032}}}"}},{"workerId":"public.us-east-1.AMKGMVI25PC0B","annotationData":{"content":"{\"boundingBox\":{\"boundingBoxes\":[{\"height\":599,\"label\":\"lock\",\"left\":1643,\"top\":232,\"width\":1159},{\"height\":207,\"label\":\"lock\",\"left\":2157,\"top\":75,\"width\":163},{\"height\":450,\"label\":\"lock\",\"left\":1249,\"top\":188,\"width\":376},{\"height\":1199,\"label\":\"handle\",\"left\":1769,\"top\":713,\"width\":344},{\"height\":269,\"label\":\"lock\",\"left\":1913,\"top\":1206,\"width\":407},{\"height\":388,\"label\":\"lock\",\"left\":1850,\"top\":1887,\"width\":557}],\"inputImageProperties\":{\"height\":3024,\"width\":4032}}}"}},{"workerId":"public.us-east-1.A30NZAZ04OUGQD","annotationData":{"content":"{\"boundingBox\":{\"boundingBoxes\":[{\"height\":692,\"label\":\"lock\",\"left\":1663,\"top\":112,\"width\":1140},{\"height\":254,\"label\":\"lock\",\"left\":1935,\"top\":1216,\"width\":351},{\"height\":377,\"label\":\"lock\",\"left\":1883,\"top\":1882,\"width\":482},{\"height\":420,\"label\":\"lock\",\"left\":1322,\"top\":199,\"width\":245},{\"height\":70,\"label\":\"lock\",\"left\":1208,\"top\":330,\"width\":123},{\"height\":1209,\"label\":\"handle\",\"left\":1804,\"top\":760,\"width\":351}],\"inputImageProperties\":{\"height\":3024,\"width\":4032}}}"}}]},{"datasetObjectId":"948","dataObject":{"s3Uri":"s3://boxlocks/box_images/IMG_6461.jpg"},"annotations":[{"workerId":"public.us-east-1.AMKGMVI25PC0B","annotationData":{"content":"{\"boundingBox\":{\"boundingBoxes\":[{\"height\":768,\"label\":\"lock\",\"left\":2658,\"top\":560,\"width\":358},{\"height\":1202,\"label\":\"lock\",\"left\":2675,\"top\":1420,\"width\":341},{\"height\":1352,\"label\":\"lock\",\"left\":1790,\"top\":1587,\"width\":792},{\"height\":835,\"label\":\"lock\",\"left\":1122,\"top\":1845,\"width\":626},{\"height\":2287,\"label\":\"lock\",\"left\":0,\"top\":819,\"width\":2233},{\"height\":860,\"label\":\"handle\",\"left\":364,\"top\":284,\"width\":776}],\"inputImageProperties\":{\"height\":4032,\"width\":3024}}}"}},{"workerId":"public.us-east-1.A19VF0AVOVX8K3","annotationData":{"content":"{\"boundingBox\":{\"boundingBoxes\":[{\"height\":1302,\"label\":\"lock\",\"left\":1832,\"top\":1570,\"width\":935},{\"height\":752,\"label\":\"lock\",\"left\":1173,\"top\":2004,\"width\":501},{\"height\":2471,\"label\":\"lock\",\"left\":39,\"top\":760,\"width\":2210},{\"height\":935,\"label\":\"handle\",\"left\":356,\"top\":351,\"width\":901}],\"inputImageProperties\":{\"height\":4032,\"width\":3024}}}"}},{"workerId":"public.us-east-1.A1T1FK3P2N408U","annotationData":{"content":"{\"boundingBox\":{\"boundingBoxes\":[{\"height\":1806,\"label\":\"lock\",\"left\":2678,\"top\":595,\"width\":346},{\"height\":1275,\"label\":\"lock\",\"left\":1897,\"top\":1575,\"width\":759},{\"height\":825,\"label\":\"lock\",\"left\":1160,\"top\":1915,\"width\":508},{\"height\":2387,\"label\":\"lock\",\"left\":26,\"top\":795,\"width\":2226},{\"height\":752,\"label\":\"handle\",\"left\":373,\"top\":352,\"width\":773},{\"height\":1098,\"label\":\"lock\",\"left\":247,\"top\":367,\"width\":568}],\"inputImageProperties\":{\"height\":4032,\"width\":3024}}}"}}]},{"datasetObjectId":"616","dataObject":{"s3Uri":"s3://boxlocks/box_images/IMG_6120.JPG"},"annotations":[{"workerId":"public.us-east-1.A19NGUFGC7KIGW","annotationData":{"content":"{\"boundingBox\":{\"boundingBoxes\":[{\"height\":479,\"label\":\"lock\",\"left\":1336,\"top\":0,\"width\":1763},{\"height\":317,\"label\":\"lock\",\"left\":1325,\"top\":1076,\"width\":485},{\"height\":384,\"label\":\"lock\",\"left\":937,\"top\":1810,\"width\":731},{\"height\":1482,\"label\":\"handle\",\"left\":898,\"top\":448,\"width\":763}],\"inputImageProperties\":{\"height\":3024,\"width\":4032}}}"}},{"workerId":"public.us-east-1.A1T1FK3P2N408U","annotationData":{"content":"{\"boundingBox\":{\"boundingBoxes\":[{\"height\":337,\"label\":\"lock\",\"left\":1310,\"top\":1060,\"width\":520},{\"height\":409,\"label\":\"lock\",\"left\":885,\"top\":1800,\"width\":784},{\"height\":442,\"label\":\"lock\",\"left\":1337,\"top\":0,\"width\":1763},{\"height\":1515,\"label\":\"handle\",\"left\":884,\"top\":446,\"width\":813}],\"inputImageProperties\":{\"height\":3024,\"width\":4032}}}"}},{"workerId":"public.us-east-1.AMKGMVI25PC0B","annotationData":{"content":"{\"boundingBox\":{\"boundingBoxes\":[{\"height\":531,\"label\":\"lock\",\"left\":1362,\"top\":0,\"width\":1822},{\"height\":1600,\"label\":\"handle\",\"left\":848,\"top\":406,\"width\":852},{\"height\":493,\"label\":\"lock\",\"left\":1268,\"top\":1013,\"width\":620},{\"height\":494,\"label\":\"lock\",\"left\":880,\"top\":1781,\"width\":814},{\"height\":469,\"label\":\"handle\",\"left\":0,\"top\":2518,\"width\":748}],\"inputImageProperties\":{\"height\":3024,\"width\":4032}}}"}}]},{"datasetObjectId":"472","dataObject":{"s3Uri":"s3://boxlocks/box_images/IMG_5975.JPG"},"annotations":[{"workerId":"public.us-east-1.A3TL2PI60EFM30","annotationData":{"content":"{\"boundingBox\":{\"boundingBoxes\":[{\"height\":1330,\"label\":\"lock\",\"left\":300,\"top\":1681,\"width\":2594},{\"height\":652,\"label\":\"lock\",\"left\":783,\"top\":952,\"width\":1680},{\"height\":1143,\"label\":\"lock\",\"left\":41,\"top\":547,\"width\":1929}],\"inputImageProperties\":{\"height\":3024,\"width\":4032}}}"}},{"workerId":"public.us-east-1.A19NGUFGC7KIGW","annotationData":{"content":"{\"boundingBox\":{\"boundingBoxes\":[{\"height\":582,\"label\":\"lock\",\"left\":1947,\"top\":1676,\"width\":618},{\"height\":399,\"label\":\"lock\",\"left\":760,\"top\":1171,\"width\":590},{\"height\":631,\"label\":\"lock\",\"left\":1216,\"top\":903,\"width\":1066},{\"height\":1175,\"label\":\"lock\",\"left\":471,\"top\":1676,\"width\":2334},{\"height\":470,\"label\":\"lock\",\"left\":1128,\"top\":528,\"width\":614},{\"height\":974,\"label\":\"lock\",\"left\":47,\"top\":659,\"width\":1868},{\"height\":268,\"label\":\"lock\",\"left\":0,\"top\":490,\"width\":1230}],\"inputImageProperties\":{\"height\":3024,\"width\":4032}}}"}},{"workerId":"public.us-east-1.AGO9QN7UEDUYL","annotationData":{"content":"{\"boundingBox\":{\"boundingBoxes\":[{\"height\":1253,\"label\":\"lock\",\"left\":358,\"top\":1646,\"width\":2441},{\"height\":705,\"label\":\"lock\",\"left\":696,\"top\":886,\"width\":1703},{\"height\":1200,\"label\":\"lock\",\"left\":0,\"top\":462,\"width\":1913}],\"inputImageProperties\":{\"height\":3024,\"width\":4032}}}"}}]}]