{"answers":[{"answerContent":{"boundingBox":{"boundingBoxes":[{"height":710,"label":"lock","left":0,"top":1764,"width":1504},{"height":376,"label":"lock","left":1412,"top":1586,"width":533},{"height":277,"label":"lock","left":1931,"top":1813,"width":348},{"height":248,"label":"lock","left":2165,"top":2133,"width":604},{"height":291,"label":"lock","left":1703,"top":2175,"width":306},{"height":398,"label":"lock","left":2577,"top":2509,"width":420},{"height":522,"label":"lock","left":1326,"top":2502,"width":683}],"inputImageProperties":{"height":3024,"width":4032}}},"submissionTime":"2020-05-09T16:59:57Z","workerId":"public.us-east-1.A4PRXDCEFH48W"},{"answerContent":{"boundingBox":{"boundingBoxes":[{"height":423,"label":"lock","left":2583,"top":2470,"width":373},{"height":284,"label":"lock","left":2173,"top":2119,"width":608},{"height":302,"label":"lock","left":1903,"top":1795,"width":428},{"height":369,"label":"lock","left":1372,"top":1606,"width":590},{"height":711,"label":"lock","left":0,"top":1791,"width":1485},{"height":243,"label":"lock","left":1138,"top":1768,"width":383},{"height":288,"label":"lock","left":1692,"top":2196,"width":337},{"height":518,"label":"lock","left":1390,"top":2506,"width":612}],"inputImageProperties":{"height":3024,"width":4032}}},"submissionTime":"2020-05-09T17:04:17Z","workerId":"public.us-east-1.A1ULHXPHPJRQVZ"},{"answerContent":{"boundingBox":{"boundingBoxes":[{"height":376,"label":"lock","left":2163,"top":2078,"width":650},{"height":405,"label":"lock","left":1366,"top":1562,"width":598},{"height":420,"label":"lock","left":1838,"top":1731,"width":613},{"height":789,"label":"lock","left":22,"top":1746,"width":1454},{"height":555,"label":"lock","left":1388,"top":2469,"width":576}],"inputImageProperties":{"height":3024,"width":4032}}},"submissionTime":"2020-05-09T17:18:54Z","workerId":"public.us-east-1.A25Z46PLOTWP8I"}]}