{"answers":[{"answerContent":{"boundingBox":{"boundingBoxes":[{"height":1028,"label":"lock","left":649,"top":1828,"width":2218},{"height":762,"label":"lock","left":76,"top":1379,"width":532},{"height":259,"label":"lock","left":922,"top":1368,"width":1277}],"inputImageProperties":{"height":3024,"width":4032}}},"submissionTime":"2020-05-09T16:57:54Z","workerId":"public.us-east-1.AJMT75QPV6HK6"},{"answerContent":{"boundingBox":{"boundingBoxes":[{"height":419,"label":"lock","left":1079,"top":1147,"width":560},{"height":364,"label":"lock","left":563,"top":1177,"width":577},{"height":1087,"label":"lock","left":0,"top":1128,"width":593},{"height":528,"label":"lock","left":970,"top":1189,"width":1301},{"height":1232,"label":"lock","left":642,"top":1730,"width":2358}],"inputImageProperties":{"height":3024,"width":4032}}},"submissionTime":"2020-05-09T17:12:31Z","workerId":"public.us-east-1.A19VF0AVOVX8K3"},{"answerContent":{"boundingBox":{"boundingBoxes":[{"height":1322,"label":"lock","left":496,"top":1702,"width":2573},{"height":426,"label":"handle","left":880,"top":1269,"width":952}],"inputImageProperties":{"height":3024,"width":4032}}},"submissionTime":"2020-05-09T17:32:27Z","workerId":"public.us-east-1.A1BVLVYJUJJFD8"}]}