{"answers":[{"answerContent":{"boundingBox":{"boundingBoxes":[{"height":1160,"label":"lock","left":1679,"top":787,"width":1524},{"height":816,"label":"handle","left":1422,"top":0,"width":877}],"inputImageProperties":{"height":3024,"width":4032}}},"submissionTime":"2020-05-09T08:15:57Z","workerId":"public.us-east-1.A16GH5GPKBX5GA"},{"answerContent":{"boundingBox":{"boundingBoxes":[{"height":1018,"label":"lock","left":1713,"top":888,"width":1450},{"height":788,"label":"handle","left":1541,"top":0,"width":701}],"inputImageProperties":{"height":3024,"width":4032}}},"submissionTime":"2020-05-09T08:17:14Z","workerId":"public.us-east-1.A1SJ936S2L4J3I"},{"answerContent":{"boundingBox":{"boundingBoxes":[{"height":775,"label":"handle","left":1527,"top":0,"width":723},{"height":969,"label":"lock","left":1673,"top":991,"width":1101}],"inputImageProperties":{"height":3024,"width":4032}}},"submissionTime":"2020-05-09T09:46:54Z","workerId":"public.us-east-1.A3KKENI2RQO12O"}]}